alohomora/__init__.py
alohomora/alohomora.dat
alohomora/authenticate.py
config/__init__.py
fynd_tornado_alohomora-0.5.0.data/data/auth_data/data_file
fynd_tornado_alohomora-0.5.0.dist-info/DESCRIPTION.rst
fynd_tornado_alohomora-0.5.0.dist-info/entry_points.txt
fynd_tornado_alohomora-0.5.0.dist-info/METADATA
fynd_tornado_alohomora-0.5.0.dist-info/metadata.json
fynd_tornado_alohomora-0.5.0.dist-info/RECORD
fynd_tornado_alohomora-0.5.0.dist-info/top_level.txt
fynd_tornado_alohomora-0.5.0.dist-info/WHEEL
helpers/__init__.py
helpers/misc_hepler.py
libs/__init__.py
libs/auth.py
